{
  "code": 1,
  "data": {
    "id": "A8ACA7AEE4F03912E040640A040269BB",
    "nipBaru": "196303251982071001",
    "nipLama": "131008460",
    "nama": "BARNAWAN",
    "gelarDepan": "",
    "gelarBelakang": "",
    "tempatLahir": "LAMPUNG UTARA",
    "tempatLahirId": "A5EB03E2205EF6A0E040640A040252AD",
    "tglLahir": "25-03-1963",
    "agama": "Islam",
    "agamaId": "1",
    "email": "barnawan.negericanda@gmail.com",
    "emailGov": "",
    "nik": "1804060703590001",
    "alamat": "KEJADIAN KECAMATAN BELALAU KABUPATEN LAMPUNG BARAT PROVINSI LAMPUNG",
    "noHp": "085658999971",
    "noTelp": "",
    "jenisPegawaiId": "15",
    "mkTahun": 40,
    "mkBulan": 9,
    "jenisPegawaiNama": "PNS Daerah Kab./Kota yang bekerja pada Kab./Kota",
    "kedudukanPnsId": "99",
    "kedudukanPnsNama": "Pensiun",
    "statusPegawai": "PNS",
    "jenisKelamin": "M",
    "jenisIdDokumenId": "1",
    "jenisIdDokumenNama": "",
    "nomorIdDocument": "1804060703590001",
    "noSeriKarpeg": "",
    "tkPendidikanTerakhirId": "25",
    "tkPendidikanTerakhir": "Diploma II",
    "pendidikanTerakhirId": "8ae48288503bd9ee01504566e26e7061",
    "pendidikanTerakhirNama": "D-II PGSD",
    "tahunLulus": "12-07-1996",
    "tmtPns": "01-02-1984",
    "tmtPensiun": "01-04-2023",
    "bupPensiun": 0,
    "tglSkPns": "30-01-1984",
    "tmtCpns": "01-07-1982",
    "tglSkCpns": "30-01-1984",
    "instansiIndukId": "A5EB03E23C37F6A0E040640A040252AD",
    "instansiIndukNama": "Pemerintah Kab. Lampung Barat",
    "satuanKerjaIndukId": "A5EB03E241B3F6A0E040640A040252AD",
    "satuanKerjaIndukNama": "Pemerintah Kab. Lampung Barat",
    "kanregId": "05",
    "kanregNama": "Kantor Regional V BKN",
    "instansiKerjaId": "A5EB03E23C37F6A0E040640A040252AD",
    "instansiKerjaNama": "Pemerintah Kab. Lampung Barat",
    "instansiKerjaKodeCepat": "5904",
    "satuanKerjaKerjaId": "A5EB03E241B3F6A0E040640A040252AD",
    "satuanKerjaKerjaNama": "Pemerintah Kab. Lampung Barat",
    "unorId": "ff80808134b2e6b70134b66e8c4d08e1",
    "unorNama": "SD NEGERI 1 BEDUDU",
    "unorIndukId": "8ae4828659703898015972b5616021b7",
    "unorIndukNama": "DINAS PENDIDIKAN DAN KEBUDAYAAN",
    "jenisJabatanId": "2",
    "jenisJabatan": "FUNGSIONAL_TERTENTU",
    "jabatanNama": "Guru Madya",
    "jabatanStrukturalId": "",
    "jabatanStrukturalNama": "",
    "jabatanFungsionalId": "ff80808133391d07013339270fb50176",
    "jabatanFungsionalNama": "",
    "jabatanFungsionalUmumId": "",
    "jabatanFungsionalUmumNama": "",
    "tmtJabatan": "01-04-2008",
    "lokasiKerjaId": "A5EB03E22CA7F6A0E040640A040252AD",
    "lokasiKerja": "BELALAU",
    "golRuangAwalId": "21",
    "golRuangAwal": "II/a",
    "golRuangAkhirId": "41",
    "golRuangAkhir": "IV/a",
    "tmtGolAkhir": "01-04-2008",
    "masaKerja": "40 tahun 9 bulan",
    "eselon": "Non Eselon",
    "eselonId": "Non Eselon",
    "eselonLevel": "Non Eselon",
    "tmtEselon": null,
    "gajiPokok": "3782400.00000000000000000000000000000000000000000000000000000",
    "kpknId": "",
    "kpknNama": "",
    "ktuaId": "A5EB03E21EEFF6A0E040640A040252AD",
    "ktuaNama": "",
    "taspenId": "101",
    "taspenNama": "",
    "jenisKawinId": "1",
    "statusPerkawinan": "Menikah",
    "statusHidup": "1",
    "tglSuratKeteranganDokter": null,
    "noSuratKeteranganDokter": "",
    "jumlahIstriSuami": null,
    "jumlahAnak": null,
    "noSuratKeteranganBebasNarkoba": "",
    "tglSuratKeteranganBebasNarkoba": null,
    "skck": "",
    "tglSkck": null,
    "akteKelahiran": "",
    "akteMeninggal": "",
    "tglMeninggal": null,
    "noNpwp": "538397628326000",
    "tglNpwp": null,
    "noAskes": "",
    "bpjs": "000762.7 080503",
    "kodePos": "34572",
    "noSpmt": "KP.140/5717/GU/V/3/PDK/1984",
    "tglSpmt": null,
    "noTaspen": "131008480",
    "bahasa": "",
    "kppnId": "A5EB03E21EC2F6A0E040640A040252AD",
    "kppnNama": "",
    "pangkatAkhir": "Pembina",
    "tglSttpl": "16-01-1984",
    "nomorSttpl": "01/PAN/LJ-II/1984",
    "nomorSkCpns": "13/G/UP/A/84",
    "nomorSkPns": "13/G/UP/A/84",
    "jenjang": "MA",
    "jabatanAsn": "",
    "kartuAsn": "A198400011023",
    "validNik": false,
    "pangkatAwal": "Pengatur Muda",
    "asnJenjangJabatan": "JFT MADYA",
    "kode_jenjang_jabatan": "23",
    "levelJabatan": "4",
    "tanggal_taspen": "",
    "tabrum2": "2",
    "kelas_jabatan": "0",
    "karis_karsu": "",
    "path": "",
    "genEmailAsn": "",
    "pertekCpnsPnsl2thNomor": "0",
    "pertekCpnsPnsl2thTanggal": "04-01-1984",
    "nomorSuratKeteranganDokter": "",
    "subJftId": "",
    "subJftNama": ""
  }
}