{
  "code": 1,
  "data": {
    "id": "A8ACA7B100D23912E040640A040269BB",
    "nipBaru": "196905201999031007",
    "nipLama": "132234812",
    "nama": "IBROHIM",
    "gelarDepan": "",
    "gelarBelakang": "S.Pd.SD",
    "tempatLahir": "LAMPUNG BARAT",
    "tempatLahirId": "A5EB03E2200AF6A0E040640A040252AD",
    "tglLahir": "20-05-1969",
    "agama": "Islam",
    "agamaId": "1",
    "email": "ibrohimnyerupa3@gmail.com",
    "emailGov": "",
    "nik": "1804112005690005",
    "alamat": "Pekon Tapak Siring",
    "noHp": "082269642454",
    "noTelp": "0",
    "jenisPegawaiId": "15",
    "mkTahun": 21,
    "mkBulan": 5,
    "jenisPegawaiNama": "PNS Daerah Kab./Kota yang bekerja pada Kab./Kota",
    "kedudukanPnsId": "01",
    "kedudukanPnsNama": "Aktif",
    "statusPegawai": "PNS",
    "jenisKelamin": "M",
    "jenisIdDokumenId": "1",
    "jenisIdDokumenNama": "",
    "nomorIdDocument": "1804112005690005",
    "noSeriKarpeg": "",
    "tkPendidikanTerakhirId": "40",
    "tkPendidikanTerakhir": "S-1/Sarjana",
    "pendidikanTerakhirId": "ff80808143056d410143096b136e6c8f",
    "pendidikanTerakhirNama": "S-1/A-IV PENDIDIKAN GURU SEKOLAH DASAR",
    "tahunLulus": "31-12-2013",
    "tmtPns": "01-03-1999",
    "tmtPensiun": null,
    "bupPensiun": 0,
    "tglSkPns": "30-12-2000",
    "tmtCpns": "01-03-1999",
    "tglSkCpns": "16-10-1999",
    "instansiIndukId": "A5EB03E23C37F6A0E040640A040252AD",
    "instansiIndukNama": "Pemerintah Kab. Lampung Barat",
    "satuanKerjaIndukId": "A5EB03E241B3F6A0E040640A040252AD",
    "satuanKerjaIndukNama": "Pemerintah Kab. Lampung Barat",
    "kanregId": "05",
    "kanregNama": "Kantor Regional V BKN",
    "instansiKerjaId": "A5EB03E23C37F6A0E040640A040252AD",
    "instansiKerjaNama": "Pemerintah Kab. Lampung Barat",
    "instansiKerjaKodeCepat": "5904",
    "satuanKerjaKerjaId": "A5EB03E241B3F6A0E040640A040252AD",
    "satuanKerjaKerjaNama": "Pemerintah Kab. Lampung Barat",
    "unorId": "ff80808134b2e6b70134bc4a937a1e2c",
    "unorNama": "SD NEGERI 2 PAGAR DEWA",
    "unorIndukId": "8ae4828659703898015972b5616021b7",
    "unorIndukNama": "DINAS PENDIDIKAN DAN KEBUDAYAAN",
    "jenisJabatanId": "2",
    "jenisJabatan": "FUNGSIONAL_TERTENTU",
    "jabatanNama": "Guru Ahli Madya",
    "jabatanStrukturalId": "",
    "jabatanStrukturalNama": "",
    "jabatanFungsionalId": "A5EB03E23F42F6A0E040640A040252AD",
    "jabatanFungsionalNama": "",
    "jabatanFungsionalUmumId": "",
    "jabatanFungsionalUmumNama": "",
    "tmtJabatan": "01-10-2021",
    "lokasiKerjaId": "A5EB03E22CABF6A0E040640A040252AD",
    "lokasiKerja": "SUKAU",
    "golRuangAwalId": "21",
    "golRuangAwal": "II/a",
    "golRuangAkhirId": "42",
    "golRuangAkhir": "IV/b",
    "tmtGolAkhir": "01-08-2025",
    "masaKerja": "21 tahun 5 bulan",
    "eselon": "Non Eselon",
    "eselonId": "Non Eselon",
    "eselonLevel": "Non Eselon",
    "tmtEselon": "01-07-2021",
    "gajiPokok": "4213500.00000000000000000000000000000000000000000000000000000",
    "kpknId": "",
    "kpknNama": "BADAN KEUANGAN DAN ASET DAERAH (BKAD)",
    "ktuaId": "",
    "ktuaNama": "",
    "taspenId": "",
    "taspenNama": "",
    "jenisKawinId": "1",
    "statusPerkawinan": "Menikah",
    "statusHidup": "1",
    "tglSuratKeteranganDokter": null,
    "noSuratKeteranganDokter": "",
    "jumlahIstriSuami": null,
    "jumlahAnak": null,
    "noSuratKeteranganBebasNarkoba": "",
    "tglSuratKeteranganBebasNarkoba": null,
    "skck": "",
    "tglSkck": null,
    "akteKelahiran": "",
    "akteMeninggal": "",
    "tglMeninggal": null,
    "noNpwp": "49.176.637.4326.000",
    "tglNpwp": "28-03-2011",
    "noAskes": "",
    "bpjs": "0000034990033",
    "kodePos": "34761",
    "noSpmt": "813.2/409/GK/A/PK/2000",
    "tglSpmt": null,
    "noTaspen": "",
    "bahasa": "",
    "kppnId": "8ae482a759b076c20159ba3f886a2fb8",
    "kppnNama": "",
    "pangkatAkhir": "Pembina Tingkat I",
    "tglSttpl": "25-08-2000",
    "nomorSttpl": "897.2/186/G/LPJ.GOL.II/2000",
    "nomorSkCpns": "813.5/1758/V/08/1999",
    "nomorSkPns": "58/GU/UP/A/200",
    "jenjang": "MA",
    "jabatanAsn": "",
    "kartuAsn": "A199900023222",
    "validNik": true,
    "pangkatAwal": "Pengatur Muda",
    "asnJenjangJabatan": "JFT MADYA",
    "kode_jenjang_jabatan": "23",
    "levelJabatan": "4",
    "tanggal_taspen": "",
    "tabrum2": "1555243291",
    "kelas_jabatan": "",
    "karis_karsu": "000121 I",
    "path": "{\"1\": {\"slug\": \"2\", \"dok_id\": \"2\", \"object\": \"A8ACA7B100D23912E040640A040269BB_513aa619860449779a6acc5983ba5eed.pdf\", \"sumber\": \"dms\", \"dok_uri\": \"A8ACA7B100D23912E040640A040269BB_513aa619860449779a6acc5983ba5eed.pdf\", \"dok_nama\": \"Dok Usul SOTK Anjab AB\"}, \"24\": {\"slug\": \"24\", \"dok_id\": \"24\", \"object\": \"A8ACA7B100D23912E040640A040269BB_29e64d02b4ab46eb9d138ce11c5c1340.pdf\", \"sumber\": \"dms\", \"dok_uri\": \"A8ACA7B100D23912E040640A040269BB_29e64d02b4ab46eb9d138ce11c5c1340.pdf\", \"dok_nama\": \"Dok Daftar Riwayat Hidup\"}, \"889\": {\"slug\": \"889\", \"dok_id\": \"889\", \"object\": \"peremajaan/usulan/889_3fc588fb-9f0f-4550-a89b-cfb3243a9812.pdf\", \"dok_uri\": \"peremajaan/usulan/889_3fc588fb-9f0f-4550-a89b-cfb3243a9812.pdf\", \"dok_nama\": \"Dok SK CPNS\"}}",
    "genEmailAsn": "",
    "pertekCpnsPnsl2thNomor": "",
    "pertekCpnsPnsl2thTanggal": null,
    "nomorSuratKeteranganDokter": "",
    "subJftId": "0",
    "subJftNama": ""
  }
}