{
  "code": 1,
  "data": {
    "id": "A8ACA7B614003912E040640A040269BB",
    "nipBaru": "197003152007011011",
    "nipLama": "460035126",
    "nama": "MUKHLIS. HS",
    "gelarDepan": "",
    "gelarBelakang": "S.Pd",
    "tempatLahir": "LAMPUNG BARAT",
    "tempatLahirId": "A5EB03E2200AF6A0E040640A040252AD",
    "tglLahir": "15-03-1970",
    "agama": "Islam",
    "agamaId": "1",
    "email": "mukhlisbelalau@gmail.com",
    "emailGov": "",
    "nik": "1804061503700003",
    "alamat": "KELURAHAN BEDUDU KEC. BELALAU KAB. LAMPUNG BARAT",
    "noHp": "082371880343",
    "noTelp": "082371880343",
    "jenisPegawaiId": "15",
    "mkTahun": 10,
    "mkBulan": 10,
    "jenisPegawaiNama": "PNS Daerah Kab./Kota yang bekerja pada Kab./Kota",
    "kedudukanPnsId": "01",
    "kedudukanPnsNama": "Aktif",
    "statusPegawai": "PNS",
    "jenisKelamin": "M",
    "jenisIdDokumenId": "1",
    "jenisIdDokumenNama": "",
    "nomorIdDocument": "1804061503700003",
    "noSeriKarpeg": "",
    "tkPendidikanTerakhirId": "40",
    "tkPendidikanTerakhir": "S-1/Sarjana",
    "pendidikanTerakhirId": "ff8080815133783a015138458f646093",
    "pendidikanTerakhirNama": "S-1 PENDIDIKAN BAHASA DAN SASTRA INDONESIA",
    "tahunLulus": "01-01-2012",
    "tmtPns": "01-04-2009",
    "tmtPensiun": null,
    "bupPensiun": 0,
    "tglSkPns": "30-03-2009",
    "tmtCpns": "01-01-2007",
    "tglSkCpns": "13-11-2007",
    "instansiIndukId": "A5EB03E23C37F6A0E040640A040252AD",
    "instansiIndukNama": "Pemerintah Kab. Lampung Barat",
    "satuanKerjaIndukId": "A5EB03E241B3F6A0E040640A040252AD",
    "satuanKerjaIndukNama": "Pemerintah Kab. Lampung Barat",
    "kanregId": "05",
    "kanregNama": "Kantor Regional V BKN",
    "instansiKerjaId": "A5EB03E23C37F6A0E040640A040252AD",
    "instansiKerjaNama": "Pemerintah Kab. Lampung Barat",
    "instansiKerjaKodeCepat": "5904",
    "satuanKerjaKerjaId": "A5EB03E241B3F6A0E040640A040252AD",
    "satuanKerjaKerjaNama": "Pemerintah Kab. Lampung Barat",
    "unorId": "ff80808134b2e6b70134b66faafe08ef",
    "unorNama": "SD NEGERI 2 BEDUDU",
    "unorIndukId": "8ae4828659703898015972b5616021b7",
    "unorIndukNama": "DINAS PENDIDIKAN DAN KEBUDAYAAN",
    "jenisJabatanId": "2",
    "jenisJabatan": "FUNGSIONAL_TERTENTU",
    "jabatanNama": "Guru Ahli Muda",
    "jabatanStrukturalId": "",
    "jabatanStrukturalNama": "",
    "jabatanFungsionalId": "A5EB03E23F44F6A0E040640A040252AD",
    "jabatanFungsionalNama": "",
    "jabatanFungsionalUmumId": "",
    "jabatanFungsionalUmumNama": "",
    "tmtJabatan": "01-04-2017",
    "lokasiKerjaId": "A5EB03E22CA7F6A0E040640A040252AD",
    "lokasiKerja": "BELALAU",
    "golRuangAwalId": "21",
    "golRuangAwal": "II/a",
    "golRuangAkhirId": "34",
    "golRuangAkhir": "III/d",
    "tmtGolAkhir": "01-04-2019",
    "masaKerja": "10 tahun 10 bulan",
    "eselon": "Non Eselon",
    "eselonId": "Non Eselon",
    "eselonLevel": "Non Eselon",
    "tmtEselon": "12-03-2010",
    "gajiPokok": "3410600.00000000000000000000000000000000000000000000000000000",
    "kpknId": "",
    "kpknNama": "LIWA",
    "ktuaId": "",
    "ktuaNama": "",
    "taspenId": "",
    "taspenNama": "",
    "jenisKawinId": "1",
    "statusPerkawinan": "Menikah",
    "statusHidup": "1",
    "tglSuratKeteranganDokter": "19-07-2007",
    "noSuratKeteranganDokter": "812/601/BPU RSD LW/2007",
    "jumlahIstriSuami": null,
    "jumlahAnak": null,
    "noSuratKeteranganBebasNarkoba": "",
    "tglSuratKeteranganBebasNarkoba": null,
    "skck": "",
    "tglSkck": null,
    "akteKelahiran": "",
    "akteMeninggal": "",
    "tglMeninggal": null,
    "noNpwp": "59.839.775.0.326.000",
    "tglNpwp": "30-12-2010",
    "noAskes": "",
    "bpjs": "0000034121349",
    "kodePos": "",
    "noSpmt": "",
    "tglSpmt": null,
    "noTaspen": "460035126",
    "bahasa": "",
    "kppnId": "A5EB03E21EC2F6A0E040640A040252AD",
    "kppnNama": "",
    "pangkatAkhir": "Penata Tingkat I",
    "tglSttpl": "17-12-2008",
    "nomorSttpl": "MUTASI",
    "nomorSkCpns": "813/60/II.05/2007",
    "nomorSkPns": "821.12/16/III.04/2009",
    "jenjang": "MU",
    "jabatanAsn": "",
    "kartuAsn": "A200900078390",
    "validNik": true,
    "pangkatAwal": "Pengatur Muda",
    "asnJenjangJabatan": "JFT MUDA",
    "kode_jenjang_jabatan": "22",
    "levelJabatan": "3",
    "tanggal_taspen": "",
    "tabrum2": "1",
    "kelas_jabatan": "1",
    "karis_karsu": "",
    "path": "",
    "genEmailAsn": "",
    "pertekCpnsPnsl2thNomor": "FF-21801000346",
    "pertekCpnsPnsl2thTanggal": "02-03-2009",
    "nomorSuratKeteranganDokter": "",
    "subJftId": "",
    "subJftNama": ""
  }
}