{
  "code": 1,
  "data": {
    "id": "d417654b-3284-4c38-8955-df696b95e5ef",
    "nipBaru": "197408122025211012",
    "nipLama": "",
    "nama": "HAMIDI",
    "gelarDepan": "",
    "gelarBelakang": "",
    "tempatLahir": "LAMPUNG BARAT",
    "tempatLahirId": "A5EB03E2200AF6A0E040640A040252AD",
    "tglLahir": "12-08-1974",
    "agama": "Islam",
    "agamaId": "1",
    "email": "h13316527@gmail.com",
    "emailGov": "",
    "nik": "1804111208740003",
    "alamat": "JALAN WISATA LUMBOK SEMINUNG",
    "noHp": "081379858733",
    "noTelp": "081379858733",
    "jenisPegawaiId": "15",
    "mkTahun": 0,
    "mkBulan": 0,
    "jenisPegawaiNama": "PNS Daerah Kab./Kota yang bekerja pada Kab./Kota",
    "kedudukanPnsId": "71",
    "kedudukanPnsNama": "PPPK Aktif",
    "statusPegawai": "PNS",
    "jenisKelamin": "M",
    "jenisIdDokumenId": "",
    "jenisIdDokumenNama": "",
    "nomorIdDocument": "1804111208740003",
    "noSeriKarpeg": "",
    "tkPendidikanTerakhirId": "15",
    "tkPendidikanTerakhir": "SLTA",
    "pendidikanTerakhirId": "8ae4828947fbda2a01481ad629e5545f",
    "pendidikanTerakhirNama": "SLTA/SMA SEDERAJAT",
    "tahunLulus": "23-05-1994",
    "tmtPns": null,
    "tmtPensiun": null,
    "bupPensiun": 0,
    "tglSkPns": null,
    "tmtCpns": "01-04-2025",
    "tglSkCpns": "30-04-2025",
    "instansiIndukId": "A5EB03E23C37F6A0E040640A040252AD",
    "instansiIndukNama": "Pemerintah Kab. Lampung Barat",
    "satuanKerjaIndukId": "A5EB03E241B3F6A0E040640A040252AD",
    "satuanKerjaIndukNama": "Pemerintah Kab. Lampung Barat",
    "kanregId": "05",
    "kanregNama": "Kantor Regional V BKN",
    "instansiKerjaId": "A5EB03E23C37F6A0E040640A040252AD",
    "instansiKerjaNama": "Pemerintah Kab. Lampung Barat",
    "instansiKerjaKodeCepat": "5904",
    "satuanKerjaKerjaId": "A5EB03E241B3F6A0E040640A040252AD",
    "satuanKerjaKerjaNama": "Pemerintah Kab. Lampung Barat",
    "unorId": "ff80808134b2e6b70134bc50c2691e5a",
    "unorNama": "SD NEGERI 2 JAGARAGA",
    "unorIndukId": "8ae4828659703898015972b5616021b7",
    "unorIndukNama": "DINAS PENDIDIKAN DAN KEBUDAYAAN",
    "jenisJabatanId": "4",
    "jenisJabatan": "FUNGSIONAL_UMUM",
    "jabatanNama": "PENGADMINISTRASI PERKANTORAN",
    "jabatanStrukturalId": "",
    "jabatanStrukturalNama": "",
    "jabatanFungsionalId": "",
    "jabatanFungsionalNama": "",
    "jabatanFungsionalUmumId": "8ae482884fde72e4014fdf1f1abe3f3c",
    "jabatanFungsionalUmumNama": "PENGADMINISTRASI PERKANTORAN",
    "tmtJabatan": "01-04-2025",
    "lokasiKerjaId": "A5EB03E22CABF6A0E040640A040252AD",
    "lokasiKerja": "SUKAU",
    "golRuangAwalId": "21",
    "golRuangAwal": "V",
    "golRuangAkhirId": "21",
    "golRuangAkhir": "V",
    "tmtGolAkhir": "01-04-2025",
    "masaKerja": "0 tahun 0 bulan",
    "eselon": "Non Eselon",
    "eselonId": "Non Eselon",
    "eselonLevel": "Non Eselon",
    "tmtEselon": null,
    "gajiPokok": "2511500.00000000000000000000000000000000000000000000000000000",
    "kpknId": "",
    "kpknNama": "LIWA",
    "ktuaId": "",
    "ktuaNama": "",
    "taspenId": "",
    "taspenNama": "",
    "jenisKawinId": "1",
    "statusPerkawinan": "Menikah",
    "statusHidup": "1",
    "tglSuratKeteranganDokter": "04-01-2025",
    "noSuratKeteranganDokter": "GALIH PRASETIO EKIN B.UTOMO '/'.NOVI SUSILOWATI",
    "jumlahIstriSuami": null,
    "jumlahAnak": null,
    "noSuratKeteranganBebasNarkoba": "400.7.22.1/4436.C/VII.02/2025",
    "tglSuratKeteranganBebasNarkoba": "04-01-2025",
    "skck": "SKCK/YANMAS/36/I/2025/INTELKAM",
    "tglSkck": "02-01-2025",
    "akteKelahiran": "",
    "akteMeninggal": "",
    "tglMeninggal": null,
    "noNpwp": "",
    "tglNpwp": null,
    "noAskes": "",
    "bpjs": "",
    "kodePos": "",
    "noSpmt": "",
    "tglSpmt": null,
    "noTaspen": "",
    "bahasa": "",
    "kppnId": "A5EB03E21EC2F6A0E040640A040252AD",
    "kppnNama": "",
    "pangkatAkhir": "Pengatur Muda",
    "tglSttpl": null,
    "nomorSttpl": "",
    "nomorSkCpns": "B/70/KPTS/IV.05/2025",
    "nomorSkPns": "",
    "jenjang": "",
    "jabatanAsn": "",
    "kartuAsn": "B202500335981",
    "validNik": true,
    "pangkatAwal": "",
    "asnJenjangJabatan": "JABATAN PELAKSANA",
    "kode_jenjang_jabatan": "",
    "levelJabatan": "1",
    "tanggal_taspen": null,
    "tabrum2": "",
    "kelas_jabatan": "",
    "karis_karsu": "",
    "path": "{\"889\": {\"slug\": \"889\", \"dok_id\": \"889\", \"object\": \"sk-instansi-A5EB03E23C37F6A0E040640A040252AD/INS.SK.01.03/sign-final/12cfc9e3b71f016f864b8f87200ae1415c0dfea327d98e414a51378d-2025-06-25T04-42-11.405087/12cfc9e3b71f016f864b8f87200ae1415c0dfea327d98e414a51378d-2025-06-25T04-42-11.405087.pdf\", \"dok_uri\": \"sk-instansi-A5EB03E23C37F6A0E040640A040252AD/INS.SK.01.03/sign-final/12cfc9e3b71f016f864b8f87200ae1415c0dfea327d98e414a51378d-2025-06-25T04-42-11.405087/12cfc9e3b71f016f864b8f87200ae1415c0dfea327d98e414a51378d-2025-06-25T04-42-11.405087.pdf\", \"dok_nama\": \"Dok SK CPNS\"}}",
    "genEmailAsn": "",
    "pertekCpnsPnsl2thNomor": "",
    "pertekCpnsPnsl2thTanggal": null,
    "nomorSuratKeteranganDokter": "",
    "subJftId": "0",
    "subJftNama": ""
  }
}