{
  "code": 1,
  "data": {
    "id": "A8ACA78B3CB13912E040640A040269BB",
    "nipBaru": "197901162011011002",
    "nipLama": "",
    "nama": "LENDRA JAYA",
    "gelarDepan": "",
    "gelarBelakang": "A.MD",
    "tempatLahir": "LAMPUNG BARAT",
    "tempatLahirId": "A5EB03E2200AF6A0E040640A040252AD",
    "tglLahir": "16-01-1979",
    "agama": "Islam",
    "agamaId": "1",
    "email": "arden.lendra@gmail.com",
    "emailGov": "",
    "nik": "1804041601790001",
    "alamat": "JL.P.TENDEAN  WAY EMPULAU ULU KECAMATAN BALIK BUKIT, LAMPUNG BARAT",
    "noHp": "082279878089",
    "noTelp": "072821086",
    "jenisPegawaiId": "15",
    "mkTahun": 10,
    "mkBulan": 3,
    "jenisPegawaiNama": "PNS Daerah Kab./Kota yang bekerja pada Kab./Kota",
    "kedudukanPnsId": "01",
    "kedudukanPnsNama": "Aktif",
    "statusPegawai": "PNS",
    "jenisKelamin": "M",
    "jenisIdDokumenId": "1",
    "jenisIdDokumenNama": "",
    "nomorIdDocument": "1804041601790001",
    "noSeriKarpeg": "",
    "tkPendidikanTerakhirId": "30",
    "tkPendidikanTerakhir": "Diploma III/Sarjana Muda",
    "pendidikanTerakhirId": "A5EB03E20DB4F6A0E040640A040252AD",
    "pendidikanTerakhirNama": "D-III TEKNIK PENGUKURAN DAN PEMETAAN",
    "tahunLulus": "01-01-2002",
    "tmtPns": "01-12-2012",
    "tmtPensiun": null,
    "bupPensiun": 0,
    "tglSkPns": "28-11-2012",
    "tmtCpns": "01-01-2011",
    "tglSkCpns": "31-12-2010",
    "instansiIndukId": "A5EB03E23C37F6A0E040640A040252AD",
    "instansiIndukNama": "Pemerintah Kab. Lampung Barat",
    "satuanKerjaIndukId": "A5EB03E241B3F6A0E040640A040252AD",
    "satuanKerjaIndukNama": "Pemerintah Kab. Lampung Barat",
    "kanregId": "05",
    "kanregNama": "Kantor Regional V BKN",
    "instansiKerjaId": "A5EB03E23C37F6A0E040640A040252AD",
    "instansiKerjaNama": "Pemerintah Kab. Lampung Barat",
    "instansiKerjaKodeCepat": "5904",
    "satuanKerjaKerjaId": "A5EB03E241B3F6A0E040640A040252AD",
    "satuanKerjaKerjaNama": "Pemerintah Kab. Lampung Barat",
    "unorId": "A8ACA73D16713912E040640A040269BB",
    "unorNama": "UPTD PERKUATAN PERMODALAN KOPERASI DAN UKM",
    "unorIndukId": "A8ACA73D166F3912E040640A040269BB",
    "unorIndukNama": "DINAS KOPERASI, UKM DAN PERDAGANGAN",
    "jenisJabatanId": "1",
    "jenisJabatan": "STRUKTURAL",
    "jabatanNama": "KEPALA UPTD PERKUATAN PERMODALAN KOPERASI DAN UKM",
    "jabatanStrukturalId": "A8ACA73D16713912E040640A040269BB",
    "jabatanStrukturalNama": "KEPALA UPTD PERKUATAN PERMODALAN KOPERASI DAN UKM",
    "jabatanFungsionalId": "",
    "jabatanFungsionalNama": "",
    "jabatanFungsionalUmumId": "",
    "jabatanFungsionalUmumNama": "",
    "tmtJabatan": "21-07-2025",
    "lokasiKerjaId": "A5EB03E22CA6F6A0E040640A040252AD",
    "lokasiKerja": "BALIK BUKIT",
    "golRuangAwalId": "23",
    "golRuangAwal": "II/c",
    "golRuangAkhirId": "32",
    "golRuangAkhir": "III/b",
    "tmtGolAkhir": "01-04-2023",
    "masaKerja": "10 tahun 3 bulan",
    "eselon": "",
    "eselonId": "41",
    "eselonLevel": "4",
    "tmtEselon": "03-01-2017",
    "gajiPokok": "2830900.00000000000000000000000000000000000000000000000000000",
    "kpknId": "",
    "kpknNama": "",
    "ktuaId": "",
    "ktuaNama": "",
    "taspenId": "",
    "taspenNama": "",
    "jenisKawinId": "1",
    "statusPerkawinan": "Menikah",
    "statusHidup": "1",
    "tglSuratKeteranganDokter": "27-12-2010",
    "noSuratKeteranganDokter": "000/042.B/III.06/2010",
    "jumlahIstriSuami": null,
    "jumlahAnak": null,
    "noSuratKeteranganBebasNarkoba": "",
    "tglSuratKeteranganBebasNarkoba": null,
    "skck": "",
    "tglSkck": null,
    "akteKelahiran": "",
    "akteMeninggal": "",
    "tglMeninggal": null,
    "noNpwp": "682830179412000",
    "tglNpwp": "23-01-2009",
    "noAskes": "",
    "bpjs": "0000201786658",
    "kodePos": "",
    "noSpmt": "800/95/III.04/2011",
    "tglSpmt": null,
    "noTaspen": "197901162011011002",
    "bahasa": "",
    "kppnId": "A5EB03E21EC2F6A0E040640A040252AD",
    "kppnNama": "",
    "pangkatAkhir": "Penata Muda Tingkat I",
    "tglSttpl": null,
    "nomorSttpl": "20.104/I.08/Diklat Prajabatan II/LAN/2012",
    "nomorSkCpns": "813/86.b/III.04/2010",
    "nomorSkPns": "821.12/154/III.04/2012",
    "jenjang": "",
    "jabatanAsn": "JABATAN PENGAWAS",
    "kartuAsn": "A201200035284",
    "validNik": true,
    "pangkatAwal": "Pengatur",
    "asnJenjangJabatan": "JABATAN PENGAWAS",
    "kode_jenjang_jabatan": "",
    "levelJabatan": "2",
    "tanggal_taspen": "",
    "tabrum2": "2326113303",
    "kelas_jabatan": "8",
    "karis_karsu": "105227K",
    "path": "{\"887\": {\"slug\": \"887\", \"dok_id\": \"887\", \"object\": \"peremajaan/usulan/887_e8a8159a-321d-4653-86c2-f66a017db5e6.pdf\", \"dok_uri\": \"peremajaan/usulan/887_e8a8159a-321d-4653-86c2-f66a017db5e6.pdf\", \"dok_nama\": \"Dok SK PNS\"}, \"888\": {\"slug\": \"888\", \"dok_id\": \"888\", \"object\": \"peremajaan/usulan/888_e8a8159a-321d-4653-86c2-f66a017db5e6.pdf\", \"dok_uri\": \"peremajaan/usulan/888_e8a8159a-321d-4653-86c2-f66a017db5e6.pdf\", \"dok_nama\": \"Dok SPMT\"}, \"889\": {\"slug\": \"889\", \"dok_id\": \"889\", \"object\": \"peremajaan/usulan/889_e8a8159a-321d-4653-86c2-f66a017db5e6.pdf\", \"dok_uri\": \"peremajaan/usulan/889_e8a8159a-321d-4653-86c2-f66a017db5e6.pdf\", \"dok_nama\": \"Dok SK CPNS\"}}",
    "genEmailAsn": "",
    "pertekCpnsPnsl2thNomor": "-",
    "pertekCpnsPnsl2thTanggal": "03-10-2011",
    "nomorSuratKeteranganDokter": "",
    "subJftId": "0",
    "subJftNama": ""
  }
}