{
  "code": 1,
  "data": {
    "id": "A8ACA7B661963912E040640A040269BB",
    "nipBaru": "198105172009061001",
    "nipLama": "",
    "nama": "JAROT KUNTO WIBOWO",
    "gelarDepan": "dr",
    "gelarBelakang": "Sp.THT-KL",
    "tempatLahir": "JAKARTA",
    "tempatLahirId": "A5EB03E21F05F6A0E040640A040252AD",
    "tglLahir": "17-05-1981",
    "agama": "Islam",
    "agamaId": "1",
    "email": "jarotkuntowibowo1981liwa@gmail.com",
    "emailGov": "kuntowibowojarot@lampungbaratkab.go.id",
    "nik": "1804041705810001",
    "alamat": "Komplek RSUD Liwa No.05-06, Kubu Perahu, Balik Bukit, Lampung Barat",
    "noHp": "085888288541",
    "noTelp": "085888288541",
    "jenisPegawaiId": "15",
    "mkTahun": 15,
    "mkBulan": 4,
    "jenisPegawaiNama": "PNS Daerah Kab./Kota yang bekerja pada Kab./Kota",
    "kedudukanPnsId": "01",
    "kedudukanPnsNama": "Aktif",
    "statusPegawai": "PNS",
    "jenisKelamin": "M",
    "jenisIdDokumenId": "1",
    "jenisIdDokumenNama": "",
    "nomorIdDocument": "1804041705810001",
    "noSeriKarpeg": "",
    "tkPendidikanTerakhirId": "40",
    "tkPendidikanTerakhir": "S-1/Sarjana",
    "pendidikanTerakhirId": "8ae48287511e3ed5015137b3fa6156b6",
    "pendidikanTerakhirNama": "S-1 KEDOKTERAN UMUM",
    "tahunLulus": "01-01-0001",
    "tmtPns": "01-06-2013",
    "tmtPensiun": null,
    "bupPensiun": 0,
    "tglSkPns": "31-05-2013",
    "tmtCpns": "01-06-2009",
    "tglSkCpns": "31-05-2013",
    "instansiIndukId": "A5EB03E23C37F6A0E040640A040252AD",
    "instansiIndukNama": "Pemerintah Kab. Lampung Barat",
    "satuanKerjaIndukId": "A5EB03E241B3F6A0E040640A040252AD",
    "satuanKerjaIndukNama": "Pemerintah Kab. Lampung Barat",
    "kanregId": "05",
    "kanregNama": "Kantor Regional V BKN",
    "instansiKerjaId": "A5EB03E23C37F6A0E040640A040252AD",
    "instansiKerjaNama": "Pemerintah Kab. Lampung Barat",
    "instansiKerjaKodeCepat": "5904",
    "satuanKerjaKerjaId": "A5EB03E241B3F6A0E040640A040252AD",
    "satuanKerjaKerjaNama": "Pemerintah Kab. Lampung Barat",
    "unorId": "8ae483c57f6de4e3017f733051c02e06",
    "unorNama": "SUB BIDANG PELAYANAN RAWAT INAP DAN TENAGA MEDIS",
    "unorIndukId": "8ae483c57f6de4e3017f731855a0228a",
    "unorIndukNama": "RSUD ALIMUDDIN UMAR",
    "jenisJabatanId": "2",
    "jenisJabatan": "FUNGSIONAL_TERTENTU",
    "jabatanNama": "Dokter Ahli Madya",
    "jabatanStrukturalId": "",
    "jabatanStrukturalNama": "",
    "jabatanFungsionalId": "A5EB03E23F48F6A0E040640A040252AD",
    "jabatanFungsionalNama": "",
    "jabatanFungsionalUmumId": "",
    "jabatanFungsionalUmumNama": "",
    "tmtJabatan": "01-06-2024",
    "lokasiKerjaId": "A5EB03E22CA6F6A0E040640A040252AD",
    "lokasiKerja": "BALIK BUKIT",
    "golRuangAwalId": "32",
    "golRuangAwal": "III/b",
    "golRuangAkhirId": "41",
    "golRuangAkhir": "IV/a",
    "tmtGolAkhir": "01-10-2024",
    "masaKerja": "15 tahun 4 bulan",
    "eselon": "Non Eselon",
    "eselonId": "Non Eselon",
    "eselonLevel": "Non Eselon",
    "tmtEselon": "03-01-2022",
    "gajiPokok": "3172300.00000000000000000000000000000000000000000000000000000",
    "kpknId": "",
    "kpknNama": "BADAN KEUANGAN DAN ASET DAERAH (BKAD)",
    "ktuaId": "",
    "ktuaNama": "",
    "taspenId": "101",
    "taspenNama": "",
    "jenisKawinId": "1",
    "statusPerkawinan": "Menikah",
    "statusHidup": "1",
    "tglSuratKeteranganDokter": "06-02-2009",
    "noSuratKeteranganDokter": "000/004/LAB/III/2009",
    "jumlahIstriSuami": null,
    "jumlahAnak": null,
    "noSuratKeteranganBebasNarkoba": "",
    "tglSuratKeteranganBebasNarkoba": null,
    "skck": "",
    "tglSkck": null,
    "akteKelahiran": "",
    "akteMeninggal": "",
    "tglMeninggal": null,
    "noNpwp": "15.136.928.7-326.000",
    "tglNpwp": "21-10-2008",
    "noAskes": "",
    "bpjs": "",
    "kodePos": "",
    "noSpmt": "800/59/III.04/2010",
    "tglSpmt": "01-04-2010",
    "noTaspen": "",
    "bahasa": "",
    "kppnId": "8ae482a759b076c20159ba3f886a2fb8",
    "kppnNama": "",
    "pangkatAkhir": "Pembina",
    "tglSttpl": "04-12-2012",
    "nomorSttpl": "46.901/I.08/DIKLAT PRAJAB III/LAN/2012",
    "nomorSkCpns": "813/26/III.04/2009",
    "nomorSkPns": "821.13/182.a/III.04/2013",
    "jenjang": "MA",
    "jabatanAsn": "",
    "kartuAsn": "A201300009562",
    "validNik": true,
    "pangkatAwal": "Penata Muda Tingkat I",
    "asnJenjangJabatan": "JFT MADYA",
    "kode_jenjang_jabatan": "23",
    "levelJabatan": "4",
    "tanggal_taspen": "",
    "tabrum2": "2982281795",
    "kelas_jabatan": "",
    "karis_karsu": "BB 05023450",
    "path": "{\"2\": {\"slug\": \"2\", \"dok_id\": \"2\", \"object\": \"dms/A8ACA7B661963912E040640A040269BB/7cdbdbea-ddc1-4b1c-bb5b-cd15475ad92a_idjnsdok_iddokumen.pdf\", \"dok_uri\": \"dms/A8ACA7B661963912E040640A040269BB/7cdbdbea-ddc1-4b1c-bb5b-cd15475ad92a_idjnsdok_iddokumen.pdf\", \"dok_nama\": \"Dok Usul SOTK Anjab ABK\"}, \"24\": {\"slug\": \"24\", \"dok_id\": \"24\", \"object\": \"dms/A8ACA7B661963912E040640A040269BB/b103c3f1-7760-41a0-921e-8c0492ee53f4_idjnsdok_iddokumen.pdf\", \"dok_uri\": \"dms/A8ACA7B661963912E040640A040269BB/b103c3f1-7760-41a0-921e-8c0492ee53f4_idjnsdok_iddokumen.pdf\", \"dok_nama\": \"Dok Daftar Riwayat Hidup\"}, \"887\": {\"slug\": \"887\", \"dok_id\": \"887\", \"object\": \"peremajaan/usulan/887_5a7dc20f-1015-488c-bd85-a61b3b72ded2.pdf\", \"dok_uri\": \"peremajaan/usulan/887_5a7dc20f-1015-488c-bd85-a61b3b72ded2.pdf\", \"dok_nama\": \"Dok SK PNS\"}, \"888\": {\"slug\": \"888\", \"dok_id\": \"888\", \"object\": \"dms/A8ACA7B661963912E040640A040269BB/1b405684-5adc-4a41-9671-8e3e4c91c03d_idjnsdok_iddokumen.pdf\", \"dok_uri\": \"dms/A8ACA7B661963912E040640A040269BB/1b405684-5adc-4a41-9671-8e3e4c91c03d_idjnsdok_iddokumen.pdf\", \"dok_nama\": \"Dok Surat Perintah Melaksanakan Tugas\"}, \"889\": {\"slug\": \"889\", \"dok_id\": \"889\", \"object\": \"peremajaan/usulan/889_5a7dc20f-1015-488c-bd85-a61b3b72ded2.pdf\", \"dok_uri\": \"peremajaan/usulan/889_5a7dc20f-1015-488c-bd85-a61b3b72ded2.pdf\", \"dok_nama\": \"Dok SK CPNS\"}}",
    "genEmailAsn": "",
    "pertekCpnsPnsl2thNomor": "FF. 21801000003",
    "pertekCpnsPnsl2thTanggal": "29-04-2013",
    "nomorSuratKeteranganDokter": "",
    "subJftId": "",
    "subJftNama": ""
  }
}