{
  "code": 1,
  "data": {
    "id": "7E85A27469FEBD8DE050640A3C036B36",
    "nipBaru": "198502122019032001",
    "nipLama": "",
    "nama": "ELLA PEBRIANA",
    "gelarDepan": "drg.",
    "gelarBelakang": "",
    "tempatLahir": "LAMPUNG UTARA",
    "tempatLahirId": "A5EB03E2205EF6A0E040640A040252AD",
    "tglLahir": "12-02-1985",
    "agama": "Islam",
    "agamaId": "1",
    "email": "ellafebriana12@gmail.com",
    "emailGov": "",
    "nik": "1803105202850006",
    "alamat": "JL. P. POLEM GG. RANDU (GG. LEBUNG) NO.145, KELURAHAN SEGALAMIDER, KECAMATAN TANJUNG KARANG BARAT, KOTA BANDAR LAMPUNG",
    "noHp": "082280334433",
    "noTelp": "082280334433",
    "jenisPegawaiId": "15",
    "mkTahun": 5,
    "mkBulan": 7,
    "jenisPegawaiNama": "PNS Daerah Kab./Kota yang bekerja pada Kab./Kota",
    "kedudukanPnsId": "01",
    "kedudukanPnsNama": "Aktif",
    "statusPegawai": "PNS",
    "jenisKelamin": "F",
    "jenisIdDokumenId": "1",
    "jenisIdDokumenNama": "",
    "nomorIdDocument": "1803105202850006",
    "noSeriKarpeg": "",
    "tkPendidikanTerakhirId": "40",
    "tkPendidikanTerakhir": "S-1/Sarjana",
    "pendidikanTerakhirId": "ff80808147fbda4a01480b5d8d747167",
    "pendidikanTerakhirNama": "S-1 KEDOKTERAN GIGI + PROFESI",
    "tahunLulus": "01-01-2013",
    "tmtPns": "01-03-2021",
    "tmtPensiun": null,
    "bupPensiun": 0,
    "tglSkPns": "15-02-2021",
    "tmtCpns": "01-03-2019",
    "tglSkCpns": "28-02-2019",
    "instansiIndukId": "A5EB03E23C37F6A0E040640A040252AD",
    "instansiIndukNama": "Pemerintah Kab. Lampung Barat",
    "satuanKerjaIndukId": "A5EB03E241B3F6A0E040640A040252AD",
    "satuanKerjaIndukNama": "Pemerintah Kab. Lampung Barat",
    "kanregId": "05",
    "kanregNama": "Kantor Regional V BKN",
    "instansiKerjaId": "A5EB03E23C37F6A0E040640A040252AD",
    "instansiKerjaNama": "Pemerintah Kab. Lampung Barat",
    "instansiKerjaKodeCepat": "5904",
    "satuanKerjaKerjaId": "A5EB03E241B3F6A0E040640A040252AD",
    "satuanKerjaKerjaNama": "Pemerintah Kab. Lampung Barat",
    "unorId": "8ae483c57f6de4e3017f733051c02e06",
    "unorNama": "SUB BIDANG PELAYANAN RAWAT INAP DAN TENAGA MEDIS",
    "unorIndukId": "8ae483c57f6de4e3017f731855a0228a",
    "unorIndukNama": "RSUD ALIMUDDIN UMAR",
    "jenisJabatanId": "2",
    "jenisJabatan": "FUNGSIONAL_TERTENTU",
    "jabatanNama": "Dokter Ahli Muda",
    "jabatanStrukturalId": "",
    "jabatanStrukturalNama": "",
    "jabatanFungsionalId": "A5EB03E23F49F6A0E040640A040252AD",
    "jabatanFungsionalNama": "",
    "jabatanFungsionalUmumId": "",
    "jabatanFungsionalUmumNama": "",
    "tmtJabatan": "01-04-2022",
    "lokasiKerjaId": "A5EB03E22CA6F6A0E040640A040252AD",
    "lokasiKerja": "BALIK BUKIT",
    "golRuangAwalId": "32",
    "golRuangAwal": "III/b",
    "golRuangAkhirId": "34",
    "golRuangAkhir": "III/d",
    "tmtGolAkhir": "01-10-2024",
    "masaKerja": "5 tahun 7 bulan",
    "eselon": "Non Eselon",
    "eselonId": "Non Eselon",
    "eselonLevel": "Non Eselon",
    "tmtEselon": "23-01-2014",
    "gajiPokok": "3121700.00000000000000000000000000000000000000000000000000000",
    "kpknId": "",
    "kpknNama": "",
    "ktuaId": "",
    "ktuaNama": "",
    "taspenId": "",
    "taspenNama": "",
    "jenisKawinId": "1",
    "statusPerkawinan": "Menikah",
    "statusHidup": "1",
    "tglSuratKeteranganDokter": "02-01-2019",
    "noSuratKeteranganDokter": "DR. MIFTAH HASANAH",
    "jumlahIstriSuami": null,
    "jumlahAnak": null,
    "noSuratKeteranganBebasNarkoba": "445/006/III.20/2019",
    "tglSuratKeteranganBebasNarkoba": "02-01-2019",
    "skck": "SKCK/DN-453/I/YAN.2.3/2019/SAT INTELKAM",
    "tglSkck": "07-01-2019",
    "akteKelahiran": "",
    "akteMeninggal": "",
    "tglMeninggal": null,
    "noNpwp": "75.829.572.9-326.000",
    "tglNpwp": null,
    "noAskes": "",
    "bpjs": "",
    "kodePos": "",
    "noSpmt": "821/277/IV.04/2019",
    "tglSpmt": "15-04-2019",
    "noTaspen": "850212190320010",
    "bahasa": "",
    "kppnId": "A5EB03E21EC2F6A0E040640A040252AD",
    "kppnNama": "",
    "pangkatAkhir": "Penata Tingkat I",
    "tglSttpl": "30-10-2019",
    "nomorSttpl": "000038559/DIKLAT PRAJABATAN III/5900/002/LAN-PEMPROV LAMPUNG/2019",
    "nomorSkCpns": "B/9 /KPTS/IV.04/2019",
    "nomorSkPns": "823/28/KPTS/IV.04/",
    "jenjang": "MU",
    "jabatanAsn": "",
    "kartuAsn": "A202100002656",
    "validNik": true,
    "pangkatAwal": "Penata Muda Tingkat I",
    "asnJenjangJabatan": "JFT MUDA",
    "kode_jenjang_jabatan": "22",
    "levelJabatan": "3",
    "tanggal_taspen": null,
    "tabrum2": "",
    "kelas_jabatan": "",
    "karis_karsu": "",
    "path": "{\"2\": {\"slug\": \"2\", \"dok_id\": \"2\", \"object\": \"dms/7E85A27469FEBD8DE050640A3C036B36/undefined_undefined_undefined_6521421b-5d06-4901-8654-2a7eee55795e.pdf\", \"dok_uri\": \"dms/7E85A27469FEBD8DE050640A3C036B36/undefined_undefined_undefined_6521421b-5d06-4901-8654-2a7eee55795e.pdf\", \"dok_nama\": \"Dok Usul SOTK Anjab ABK\"}, \"24\": {\"slug\": \"24\", \"dok_id\": \"24\", \"object\": \"dms/7E85A27469FEBD8DE050640A3C036B36/undefined_undefined_undefined_a225199f-c86b-4ec0-9299-8c29ceaae4a7.pdf\", \"dok_uri\": \"dms/7E85A27469FEBD8DE050640A3C036B36/undefined_undefined_undefined_a225199f-c86b-4ec0-9299-8c29ceaae4a7.pdf\", \"dok_nama\": \"Dok Daftar Riwayat Hidup\"}, \"887\": {\"slug\": \"887\", \"dok_id\": \"887\", \"object\": \"peremajaan/usulan/858_94bf63b1-7376-493e-9e51-4201b986ba75.pdf\", \"dok_uri\": \"peremajaan/usulan/858_94bf63b1-7376-493e-9e51-4201b986ba75.pdf\", \"dok_nama\": \"Dok SK PNS\"}, \"888\": {\"slug\": \"888\", \"dok_id\": \"888\", \"object\": \"peremajaan/usulan/888_4232fb6f-fb7a-4ce8-a5ab-87c16d125810.pdf\", \"dok_uri\": \"peremajaan/usulan/888_4232fb6f-fb7a-4ce8-a5ab-87c16d125810.pdf\", \"dok_nama\": \"Dok Surat Perintah Melaksanakan Tugas\"}, \"889\": {\"slug\": \"889\", \"dok_id\": \"889\", \"object\": \"peremajaan/usulan/889_4232fb6f-fb7a-4ce8-a5ab-87c16d125810.pdf\", \"dok_uri\": \"peremajaan/usulan/889_4232fb6f-fb7a-4ce8-a5ab-87c16d125810.pdf\", \"dok_nama\": \"Dok SK CPNS\"}}",
    "genEmailAsn": "",
    "pertekCpnsPnsl2thNomor": "",
    "pertekCpnsPnsl2thTanggal": null,
    "nomorSuratKeteranganDokter": "",
    "subJftId": "",
    "subJftNama": ""
  }
}