{
  "code": 1,
  "data": {
    "id": "ff8080817aba3e18017abbdd3aa12de3",
    "nipBaru": "198507232022212021",
    "nipLama": "",
    "nama": "SITI YULLAIKAH",
    "gelarDepan": "",
    "gelarBelakang": "S.Pd.",
    "tempatLahir": "BLORA",
    "tempatLahirId": "A5EB03E21FF0F6A0E040640A040252AD",
    "tglLahir": "23-07-1985",
    "agama": "Islam",
    "agamaId": "1",
    "email": "sitiyullaika75@gmail.com",
    "emailGov": "",
    "nik": "1804096307850002",
    "alamat": "Jln Pelajar Srirejo Kel.Banding Agung",
    "noHp": "082257627448",
    "noTelp": "082257627448",
    "jenisPegawaiId": "15",
    "mkTahun": 0,
    "mkBulan": 0,
    "jenisPegawaiNama": "PNS Daerah Kab./Kota yang bekerja pada Kab./Kota",
    "kedudukanPnsId": "71",
    "kedudukanPnsNama": "PPPK Aktif",
    "statusPegawai": "PNS",
    "jenisKelamin": "F",
    "jenisIdDokumenId": "1",
    "jenisIdDokumenNama": "",
    "nomorIdDocument": "1804096307850002",
    "noSeriKarpeg": "",
    "tkPendidikanTerakhirId": "40",
    "tkPendidikanTerakhir": "S-1/Sarjana",
    "pendidikanTerakhirId": "ff808081523eb3030152442595961abb",
    "pendidikanTerakhirNama": "S-1 PENDIDIKAN GURU SEKOLAH DASAR",
    "tahunLulus": "17-09-2014",
    "tmtPns": "01-03-2022",
    "tmtPensiun": null,
    "bupPensiun": 0,
    "tglSkPns": null,
    "tmtCpns": "01-03-2022",
    "tglSkCpns": "12-04-2022",
    "instansiIndukId": "A5EB03E23C37F6A0E040640A040252AD",
    "instansiIndukNama": "Pemerintah Kab. Lampung Barat",
    "satuanKerjaIndukId": "A5EB03E241B3F6A0E040640A040252AD",
    "satuanKerjaIndukNama": "Pemerintah Kab. Lampung Barat",
    "kanregId": "05",
    "kanregNama": "Kantor Regional V BKN",
    "instansiKerjaId": "A5EB03E23C37F6A0E040640A040252AD",
    "instansiKerjaNama": "Pemerintah Kab. Lampung Barat",
    "instansiKerjaKodeCepat": "5904",
    "satuanKerjaKerjaId": "A5EB03E241B3F6A0E040640A040252AD",
    "satuanKerjaKerjaNama": "Pemerintah Kab. Lampung Barat",
    "unorId": "ff80808134b2e6b70134bc573d271e7e",
    "unorNama": "SD NEGERI 1 BANDING AGUNG",
    "unorIndukId": "8ae4828659703898015972b5616021b7",
    "unorIndukNama": "DINAS PENDIDIKAN DAN KEBUDAYAAN",
    "jenisJabatanId": "2",
    "jenisJabatan": "FUNGSIONAL_TERTENTU",
    "jabatanNama": "Guru Ahli Pertama",
    "jabatanStrukturalId": "",
    "jabatanStrukturalNama": "",
    "jabatanFungsionalId": "ff80808132b9d98c0132cd178bc8056e",
    "jabatanFungsionalNama": "",
    "jabatanFungsionalUmumId": "",
    "jabatanFungsionalUmumNama": "",
    "tmtJabatan": "28-02-2022",
    "lokasiKerjaId": "A5EB03E22F0BF6A0E040640A040252AD",
    "lokasiKerja": "SUOH",
    "golRuangAwalId": "31",
    "golRuangAwal": "IX",
    "golRuangAkhirId": "31",
    "golRuangAkhir": "IX",
    "tmtGolAkhir": "01-03-2022",
    "masaKerja": "0 tahun 0 bulan",
    "eselon": "Non Eselon",
    "eselonId": "Non Eselon",
    "eselonLevel": "Non Eselon",
    "tmtEselon": null,
    "gajiPokok": "0.00000000000000000000000000000000000000000000000000000",
    "kpknId": "",
    "kpknNama": "",
    "ktuaId": "",
    "ktuaNama": "",
    "taspenId": "",
    "taspenNama": "",
    "jenisKawinId": "1",
    "statusPerkawinan": "Menikah",
    "statusHidup": "1",
    "tglSuratKeteranganDokter": "29-12-2021",
    "noSuratKeteranganDokter": "ELLIS SULYANAH / TENDRY SEPTA",
    "jumlahIstriSuami": null,
    "jumlahAnak": null,
    "noSuratKeteranganBebasNarkoba": "441/9017/VII.02/2021",
    "tglSuratKeteranganBebasNarkoba": "29-12-2021",
    "skck": "SKCK/YANMAS/006004/VI/2021/INTELKAM",
    "tglSkck": "12-10-2021",
    "akteKelahiran": "",
    "akteMeninggal": "",
    "tglMeninggal": "01-01-0001",
    "noNpwp": "",
    "tglNpwp": "01-01-0001",
    "noAskes": "",
    "bpjs": "",
    "kodePos": "",
    "noSpmt": "",
    "tglSpmt": null,
    "noTaspen": "",
    "bahasa": "",
    "kppnId": "A5EB03E21C9CF6A0E040640A040252AD",
    "kppnNama": "",
    "pangkatAkhir": "Penata Muda",
    "tglSttpl": null,
    "nomorSttpl": "",
    "nomorSkCpns": "B/82/KPTS/IV.04/2022",
    "nomorSkPns": "",
    "jenjang": "PT",
    "jabatanAsn": "",
    "kartuAsn": "B202200127672",
    "validNik": true,
    "pangkatAwal": "",
    "asnJenjangJabatan": "JFT PERTAMA",
    "kode_jenjang_jabatan": "21",
    "levelJabatan": "2",
    "tanggal_taspen": null,
    "tabrum2": "",
    "kelas_jabatan": "",
    "karis_karsu": "",
    "path": "",
    "genEmailAsn": "",
    "pertekCpnsPnsl2thNomor": "",
    "pertekCpnsPnsl2thTanggal": null,
    "nomorSuratKeteranganDokter": "",
    "subJftId": "127",
    "subJftNama": ""
  }
}