{
  "code": 1,
  "data": {
    "id": "51FD5B9833E062FEE050640A2A022E68",
    "nipBaru": "199201222017081001",
    "nipLama": "",
    "nama": "RAUHIL IKHWAN",
    "gelarDepan": "",
    "gelarBelakang": "S.Pd",
    "tempatLahir": "SIMEULUE",
    "tempatLahirId": "A5EB03E22047F6A0E040640A040252AD",
    "tglLahir": "22-01-1992",
    "agama": "Islam",
    "agamaId": "1",
    "email": "rauhilikhwan92@gmail.com",
    "emailGov": "",
    "nik": "1109072201920001",
    "alamat": "Pekon Karang Agung. Kecamatan Waytenong, Kabupaten Lampung Barat.",
    "noHp": "082297168031",
    "noTelp": "082297168031",
    "jenisPegawaiId": "15",
    "mkTahun": 8,
    "mkBulan": 3,
    "jenisPegawaiNama": "PNS Daerah Kab./Kota yang bekerja pada Kab./Kota",
    "kedudukanPnsId": "01",
    "kedudukanPnsNama": "Aktif",
    "statusPegawai": "PNS",
    "jenisKelamin": "M",
    "jenisIdDokumenId": "1",
    "jenisIdDokumenNama": "",
    "nomorIdDocument": "1109072201920001",
    "noSeriKarpeg": "",
    "tkPendidikanTerakhirId": "40",
    "tkPendidikanTerakhir": "S-1/Sarjana",
    "pendidikanTerakhirId": "ff8080815252a7a7015257aa17d06c02",
    "pendidikanTerakhirNama": "S-1 PENDIDIKAN GURU SEKOLAH DASAR",
    "tahunLulus": "01-01-2015",
    "tmtPns": "01-02-2019",
    "tmtPensiun": null,
    "bupPensiun": 0,
    "tglSkPns": "31-01-2019",
    "tmtCpns": "01-08-2017",
    "tglSkCpns": "24-07-2017",
    "instansiIndukId": "A5EB03E23C37F6A0E040640A040252AD",
    "instansiIndukNama": "Pemerintah Kab. Lampung Barat",
    "satuanKerjaIndukId": "A5EB03E241B3F6A0E040640A040252AD",
    "satuanKerjaIndukNama": "Pemerintah Kab. Lampung Barat",
    "kanregId": "05",
    "kanregNama": "Kantor Regional V BKN",
    "instansiKerjaId": "A5EB03E23C37F6A0E040640A040252AD",
    "instansiKerjaNama": "Pemerintah Kab. Lampung Barat",
    "instansiKerjaKodeCepat": "5904",
    "satuanKerjaKerjaId": "A5EB03E241B3F6A0E040640A040252AD",
    "satuanKerjaKerjaNama": "Pemerintah Kab. Lampung Barat",
    "unorId": "ff80808134b2e6b70134bc3c17711dcb",
    "unorNama": "SD NEGERI 1 FAJAR BULAN",
    "unorIndukId": "8ae4828659703898015972b5616021b7",
    "unorIndukNama": "DINAS PENDIDIKAN DAN KEBUDAYAAN",
    "jenisJabatanId": "2",
    "jenisJabatan": "FUNGSIONAL_TERTENTU",
    "jabatanNama": "Guru Ahli Muda",
    "jabatanStrukturalId": "",
    "jabatanStrukturalNama": "",
    "jabatanFungsionalId": "A5EB03E23F44F6A0E040640A040252AD",
    "jabatanFungsionalNama": "",
    "jabatanFungsionalUmumId": "",
    "jabatanFungsionalUmumNama": "",
    "tmtJabatan": "07-07-2022",
    "lokasiKerjaId": "ff8080814b224047014b24ac9aeb4bbe",
    "lokasiKerja": "PAGAR DEWA",
    "golRuangAwalId": "31",
    "golRuangAwal": "III/a",
    "golRuangAkhirId": "34",
    "golRuangAkhir": "III/d",
    "tmtGolAkhir": "01-04-2025",
    "masaKerja": "8 tahun 3 bulan",
    "eselon": "Non Eselon",
    "eselonId": "Non Eselon",
    "eselonLevel": "Non Eselon",
    "tmtEselon": null,
    "gajiPokok": "2579400.00000000000000000000000000000000000000000000000000000",
    "kpknId": "",
    "kpknNama": "",
    "ktuaId": "",
    "ktuaNama": "",
    "taspenId": "",
    "taspenNama": "",
    "jenisKawinId": "1",
    "statusPerkawinan": "Menikah",
    "statusHidup": "1",
    "tglSuratKeteranganDokter": "03-07-2017",
    "noSuratKeteranganDokter": "GUSTI FUNGANI HARTI, SP.PD",
    "jumlahIstriSuami": null,
    "jumlahAnak": null,
    "noSuratKeteranganBebasNarkoba": "445/1793/2017",
    "tglSuratKeteranganBebasNarkoba": "03-07-2017",
    "skck": "SKCK/YANMIN/637/VII/2017/INTELKAM",
    "tglSkck": "03-07-2017",
    "akteKelahiran": "",
    "akteMeninggal": "",
    "tglMeninggal": null,
    "noNpwp": "825513740106000",
    "tglNpwp": null,
    "noAskes": "",
    "bpjs": "0000212792736",
    "kodePos": "",
    "noSpmt": "821/989/IV.04/2017",
    "tglSpmt": "06-12-2017",
    "noTaspen": "920122170810010",
    "bahasa": "",
    "kppnId": "A5EB03E21EC2F6A0E040640A040252AD",
    "kppnNama": "",
    "pangkatAkhir": "Penata Tingkat I",
    "tglSttpl": "23-07-2018",
    "nomorSttpl": "00006316/DIKLAT PRAJABATAN III/5900/002/LAN-PEMPROV LAMPUNG/2018",
    "nomorSkCpns": "B/41/KPTS/IV.04/2017",
    "nomorSkPns": "823/104/KPTS/IV.04/2019",
    "jenjang": "MU",
    "jabatanAsn": "",
    "kartuAsn": "A201900026713",
    "validNik": true,
    "pangkatAwal": "Penata Muda",
    "asnJenjangJabatan": "JFT MUDA",
    "kode_jenjang_jabatan": "22",
    "levelJabatan": "3",
    "tanggal_taspen": null,
    "tabrum2": "",
    "kelas_jabatan": "",
    "karis_karsu": "",
    "path": "{\"2\": {\"slug\": \"2\", \"dok_id\": \"2\", \"object\": \"dms/51FD5B9833E062FEE050640A2A022E68/undefined_undefined_undefined_5212f5ba-88c7-41a3-bce7-2b6d9d29d2fa.pdf\", \"dok_uri\": \"dms/51FD5B9833E062FEE050640A2A022E68/undefined_undefined_undefined_5212f5ba-88c7-41a3-bce7-2b6d9d29d2fa.pdf\", \"dok_nama\": \"Dok Usul SOTK Anjab ABK\"}, \"24\": {\"slug\": \"24\", \"dok_id\": \"24\", \"object\": \"dms/51FD5B9833E062FEE050640A2A022E68/undefined_undefined_undefined_f0196096-a83e-4404-9664-5c4fdfd18820.pdf\", \"dok_uri\": \"dms/51FD5B9833E062FEE050640A2A022E68/undefined_undefined_undefined_f0196096-a83e-4404-9664-5c4fdfd18820.pdf\", \"dok_nama\": \"Dok Daftar Riwayat Hidup\"}, \"887\": {\"slug\": \"887\", \"dok_id\": \"887\", \"object\": \"pns/51FD5B9833E062FEE050640A2A022E68/sk_pns/56a9912e-41e8-5b44-93ba-193c2057f5c42023-09-27 17:28:15.pdf\", \"dok_uri\": \"pns/51FD5B9833E062FEE050640A2A022E68/sk_pns/56a9912e-41e8-5b44-93ba-193c2057f5c42023-09-27 17:28:15.pdf\", \"dok_nama\": \"Dok SK PNS\"}, \"889\": {\"slug\": \"889\", \"dok_id\": \"889\", \"object\": \"peremajaan/usulan/889_ef083d83-2e43-4ab4-bcc0-c6956a3920ee.pdf\", \"dok_uri\": \"peremajaan/usulan/889_ef083d83-2e43-4ab4-bcc0-c6956a3920ee.pdf\", \"dok_nama\": \"Dok SK CPNS\"}}",
    "genEmailAsn": "",
    "pertekCpnsPnsl2thNomor": "",
    "pertekCpnsPnsl2thTanggal": null,
    "nomorSuratKeteranganDokter": "",
    "subJftId": "",
    "subJftNama": ""
  }
}