{
  "code": 1,
  "data": {
    "id": "7E85A2748870BD8DE050640A3C036B36",
    "nipBaru": "199506092019031001",
    "nipLama": "",
    "nama": "MIFTAHUL KHOIRI",
    "gelarDepan": "",
    "gelarBelakang": "S.E.",
    "tempatLahir": "OGAN KOMERING ULU TIMUR",
    "tempatLahirId": "A5EB03E22094F6A0E040640A040252AD",
    "tglLahir": "09-06-1995",
    "agama": "Islam",
    "agamaId": "1",
    "email": "miftahul.khoiri92@gmail.com",
    "emailGov": "",
    "nik": "1608120906950002",
    "alamat": "SRIKATON RT/RW 010/002, KECAMATAN BUAY MADANGTIMUR, KABUPATEN OKU TIMUR, SUMSEL 32161",
    "noHp": "081246454576",
    "noTelp": "081246454576",
    "jenisPegawaiId": "15",
    "mkTahun": 4,
    "mkBulan": 1,
    "jenisPegawaiNama": "PNS Daerah Kab./Kota yang bekerja pada Kab./Kota",
    "kedudukanPnsId": "01",
    "kedudukanPnsNama": "Aktif",
    "statusPegawai": "PNS",
    "jenisKelamin": "M",
    "jenisIdDokumenId": "1",
    "jenisIdDokumenNama": "",
    "nomorIdDocument": "1608120906950002",
    "noSeriKarpeg": "",
    "tkPendidikanTerakhirId": "40",
    "tkPendidikanTerakhir": "S-1/Sarjana",
    "pendidikanTerakhirId": "75CCE6AB2B066117E050640A29036030",
    "pendidikanTerakhirNama": "S-1 EKONOMI PERDAGANGAN",
    "tahunLulus": "29-07-2017",
    "tmtPns": "01-03-2021",
    "tmtPensiun": null,
    "bupPensiun": 0,
    "tglSkPns": "15-02-2021",
    "tmtCpns": "01-03-2019",
    "tglSkCpns": "28-02-2019",
    "instansiIndukId": "A5EB03E23C37F6A0E040640A040252AD",
    "instansiIndukNama": "Pemerintah Kab. Lampung Barat",
    "satuanKerjaIndukId": "A5EB03E241B3F6A0E040640A040252AD",
    "satuanKerjaIndukNama": "Pemerintah Kab. Lampung Barat",
    "kanregId": "05",
    "kanregNama": "Kantor Regional V BKN",
    "instansiKerjaId": "A5EB03E23C37F6A0E040640A040252AD",
    "instansiKerjaNama": "Pemerintah Kab. Lampung Barat",
    "instansiKerjaKodeCepat": "5904",
    "satuanKerjaKerjaId": "A5EB03E241B3F6A0E040640A040252AD",
    "satuanKerjaKerjaNama": "Pemerintah Kab. Lampung Barat",
    "unorId": "A8ACA73D168F3912E040640A040269BB",
    "unorNama": "BIDANG PENGELOLAAN DAN PENGEMBANGAN PASAR",
    "unorIndukId": "A8ACA73D166F3912E040640A040269BB",
    "unorIndukNama": "DINAS KOPERASI, UKM DAN PERDAGANGAN",
    "jenisJabatanId": "4",
    "jenisJabatan": "FUNGSIONAL_UMUM",
    "jabatanNama": "ANALIS MUTU PRODUK",
    "jabatanStrukturalId": "",
    "jabatanStrukturalNama": "",
    "jabatanFungsionalId": "",
    "jabatanFungsionalNama": "",
    "jabatanFungsionalUmumId": "482AE39CE8D34E20E050640A2A02304F",
    "jabatanFungsionalUmumNama": "ANALIS MUTU PRODUK",
    "tmtJabatan": "14-02-2019",
    "lokasiKerjaId": "A5EB03E22CA6F6A0E040640A040252AD",
    "lokasiKerja": "BALIK BUKIT",
    "golRuangAwalId": "31",
    "golRuangAwal": "III/a",
    "golRuangAkhirId": "32",
    "golRuangAkhir": "III/b",
    "tmtGolAkhir": "01-04-2023",
    "masaKerja": "4 tahun 1 bulan",
    "eselon": "Non Eselon",
    "eselonId": "Non Eselon",
    "eselonLevel": "Non Eselon",
    "tmtEselon": null,
    "gajiPokok": "2744500.00000000000000000000000000000000000000000000000000000",
    "kpknId": "",
    "kpknNama": "LIWA",
    "ktuaId": "",
    "ktuaNama": "",
    "taspenId": "",
    "taspenNama": "",
    "jenisKawinId": "4",
    "statusPerkawinan": "Belum Kawin",
    "statusHidup": "1",
    "tglSuratKeteranganDokter": "08-01-2019",
    "noSuratKeteranganDokter": "DR. IDA T. ASNADI",
    "jumlahIstriSuami": null,
    "jumlahAnak": null,
    "noSuratKeteranganBebasNarkoba": "023/LAB/RSUD/2019",
    "tglSuratKeteranganBebasNarkoba": "02-01-2019",
    "skck": "SKCK/YANMAS/00109/I/2019/SAT INTELKAM",
    "tglSkck": "03-01-2019",
    "akteKelahiran": "",
    "akteMeninggal": "",
    "tglMeninggal": null,
    "noNpwp": "852282102302000",
    "tglNpwp": null,
    "noAskes": "",
    "bpjs": "",
    "kodePos": "",
    "noSpmt": "821/277/IV.04/2019",
    "tglSpmt": "15-04-2019",
    "noTaspen": "",
    "bahasa": "",
    "kppnId": "A5EB03E21EC2F6A0E040640A040252AD",
    "kppnNama": "",
    "pangkatAkhir": "Penata Muda Tingkat I",
    "tglSttpl": "02-11-2020",
    "nomorSttpl": "00037066/LATSAR CPNS III/5900/017/LAN-PEMPROV LAMPUNG/2020",
    "nomorSkCpns": "B/9/KPTS/IV.04/2019",
    "nomorSkPns": "823/28/KPTS/IV.04/2021",
    "jenjang": "",
    "jabatanAsn": "",
    "kartuAsn": "A202100037937",
    "validNik": true,
    "pangkatAwal": "Penata Muda",
    "asnJenjangJabatan": "JABATAN PELAKSANA",
    "kode_jenjang_jabatan": "",
    "levelJabatan": "1",
    "tanggal_taspen": null,
    "tabrum2": "",
    "kelas_jabatan": "",
    "karis_karsu": "-",
    "path": "{\"887\": {\"slug\": \"887\", \"dok_id\": \"887\", \"object\": \"peremajaan/usulan/887_7bf45052-feae-48d2-a01f-72e4c63c36c5.pdf\", \"dok_uri\": \"peremajaan/usulan/887_7bf45052-feae-48d2-a01f-72e4c63c36c5.pdf\", \"dok_nama\": \"Dok SK PNS\"}, \"888\": {\"slug\": \"888\", \"dok_id\": \"888\", \"object\": \"peremajaan/usulan/888_7bf45052-feae-48d2-a01f-72e4c63c36c5.pdf\", \"dok_uri\": \"peremajaan/usulan/888_7bf45052-feae-48d2-a01f-72e4c63c36c5.pdf\", \"dok_nama\": \"Dok SPMT\"}, \"889\": {\"slug\": \"889\", \"dok_id\": \"889\", \"object\": \"peremajaan/usulan/889_7bf45052-feae-48d2-a01f-72e4c63c36c5.pdf\", \"dok_uri\": \"peremajaan/usulan/889_7bf45052-feae-48d2-a01f-72e4c63c36c5.pdf\", \"dok_nama\": \"Dok SK CPNS\"}}",
    "genEmailAsn": "",
    "pertekCpnsPnsl2thNomor": "",
    "pertekCpnsPnsl2thTanggal": null,
    "nomorSuratKeteranganDokter": "",
    "subJftId": "0",
    "subJftNama": ""
  }
}